brain/__init__.py
brain/__main__.py
brain/errors.py
brain/install.py
brain/rest.py
brain/rights.py
brain/service.py
brain/upgrade.py
brain/define/.git
brain/define/README.md
brain/define/errors.json
brain/define/key.json
brain/define/permission.json
brain/define/user.json
brain/define/verify.json
brain/helpers/__init__.py
brain/helpers/access.py
brain/helpers/users.py
brain/records/__init__.py
brain/records/key.py
brain/records/permission.py
brain/records/user.py
brain/upgrades/__init__.py
brain/upgrades/v1_0_1_v1_1_0.py
brain/upgrades/v1_1_0_v1_1_1.py
brain/upgrades/v1_1_1_v2_2_0.py
brain/upgrades/v2_2_0_v2_3_0.py
brain2_oc-2.4.2.dist-info/METADATA
brain2_oc-2.4.2.dist-info/WHEEL
brain2_oc-2.4.2.dist-info/entry_points.txt
brain2_oc-2.4.2.dist-info/licenses/LICENSE
brain2_oc-2.4.2.dist-info/RECORD
