Metadata-Version: 2.4
Name: brain2_oc
Version: 2.4.2
Summary: Brain contains a service to manage users and permissions
Project-URL: Documentation, https://github.com/ouroboroscoding/brain2
Project-URL: Source, https://github.com/ouroboroscoding/brain2
Project-URL: Tracker, https://github.com/ouroboroscoding/brain2/issues
Author-email: "Chris Nasr - Ouroboros Coding Inc." <chris@ouroboroscoding.com>
Maintainer-email: "Chris Nasr - Ouroboros Coding Inc." <chris@ouroboroscoding.com>
License-File: LICENSE
Requires-Python: >=3.10
Requires-Dist: body-oc<2.3,>=2.2.0
Requires-Dist: config-oc<1.2,>=1.1.0
Requires-Dist: define-oc<1.1,>=1.0.5
Requires-Dist: email-smtp<1.1,>=1.0.1
Requires-Dist: google-api-python-client>=2.168.0
Requires-Dist: google-auth-oauthlib<1.3,>=1.2.2
Requires-Dist: jsonb<1.1,>=1.0.0
Requires-Dist: namedredis<1.1,>=1.0.2
Requires-Dist: rest-mysql<1.3,>=1.2.5
Requires-Dist: strings-oc<1.1,>=1.0.7
Requires-Dist: tools-oc<1.3,>=1.2.5
Requires-Dist: undefined-oc<1.1,>=1.0.0
Requires-Dist: upgrade-oc<1.2,>=1.1.0
